dbutils.py
sheetfetcher.py
trace.py
somutils/__init__.py
somutils/config.py
somutils/config_test.py
somutils/dbutils.py
somutils/dbutils_test.py
somutils/erptree.py
somutils/erptree_test.py
somutils/isodates.py
somutils/isodates_test.py
somutils/pathlib.py
somutils/sequence.py
somutils/sheetfetcher.py
somutils/testutils.py
somutils/trace.py
somutils/tsv.py
somutils/tsv_test.py
somutils-1.10.0.data/scripts/activate_wrapper.sh
somutils-1.10.0.data/scripts/enable_destructive_tests.py
somutils-1.10.0.data/scripts/sql2csv.py
somutils-1.10.0.data/scripts/venv
somutils-1.10.0.dist-info/METADATA
somutils-1.10.0.dist-info/WHEEL
somutils-1.10.0.dist-info/top_level.txt
somutils-1.10.0.dist-info/RECORD
