Metadata-Version: 2.1
Name: somutils
Version: 1.10.0
Summary: Tools we use at Somenergia and can be useful
Home-page: https://github.com/Som-Energia/somenergia-utils
Author: César López Ramírez
Author-email: cesar.lopez@somenergia.coop
License: GNU General Public License v3 or later (GPLv3+)
Classifier: Programming Language :: Python
Classifier: Programming Language :: Python :: 2
Classifier: Environment :: Console
Classifier: Topic :: Software Development :: Libraries :: Python Modules
Classifier: Intended Audience :: Developers
Classifier: Development Status :: 5 - Production/Stable
Classifier: License :: OSI Approved :: GNU General Public License v3 or later (GPLv3+)
Classifier: Operating System :: OS Independent
Requires-Dist: yamlns >=0.7
Requires-Dist: consolemsg
Requires-Dist: pytz
Requires-Dist: csv342
Requires-Dist: google-auth
Requires-Dist: PyOpenSSL
Requires-Dist: psycopg2-binary
Requires-Dist: decorator
Requires-Dist: gspread >=4
Requires-Dist: python-dateutil >=2.9.0
Requires-Dist: contextlib2
